paste2file/__init__.py
paste2file/__main__.py
paste2file/main.py
paste2file-0.1.2.dist-info/METADATA
paste2file-0.1.2.dist-info/WHEEL
paste2file-0.1.2.dist-info/entry_points.txt
paste2file-0.1.2.dist-info/top_level.txt
paste2file-0.1.2.dist-info/RECORD
