Metadata-Version: 2.4
Name: paste2file
Version: 0.1.2
Summary: paste clipboard fast to file
Project-URL: Homepage, https://github.com/fxyzbtc/paste2file
Project-URL: Repository, https://github.com/fxyzbtc/paste2file
Classifier: Programming Language :: Python :: 3
Classifier: Operating System :: OS Independent
Classifier: Topic :: Utilities
Requires-Python: >=3.12
Requires-Dist: keyboard>=0.13.5
Requires-Dist: loguru>=0.7.3
Requires-Dist: pydantic>=2.11.3
Requires-Dist: pyperclip>=1.9.0
Requires-Dist: pillow>=10.0.0
Requires-Dist: tqdm>=4.67.1
Requires-Dist: typer>=0.12.5
